{
  "title": "Olta",
  "description": "Tek bir kayık, sabırlı bir el ve gergin bir misina — balığı ısırma anında yakala, kopmadan çek.",
  "dateAdded": "2026-06-10",
  "tags": ["arcade", "refleks", "zamanlama", "özgün"],
  "controls": "↑/↓ veya W/S: oltayı indir-çıkar · Boşluk: ısırınca yakala, sonra tut/bırak ile çek · R: yeniden başla",
  "howToPlay": "Olta, klasik balık tutmanın iki ayrı el becerisini — doğru anda yakalama ve gerilimi yönetme — tek bir 90 saniyelik turda birleştiren özgün bir refleks oyunudur. Yukarıda küçük bir kayık, ondan suya inen bir misina ve ucundaki turuncu yem var; aşağıda renkli balıklar farklı derinliklerde sağa-sola süzülüyor. Mavi küçük balıklar yüzeye yakın gezer (1 puan), turuncu orta balıklar orta katmandadır (3 puan), altın büyük balıklar dipte yavaşça dolaşır (8 puan); zaman zaman beliren mor denizanaları ise tehlikedir (-2 puan ve tur kaybı). Yemi yukarı-aşağı oynatmak için ↑/↓ veya W/S kullan; mobilde sağdaki ▲ ve ▼ düğmeleri aynı işi yapar. Yem bir balığın yakınına geldiğinde balık yeme yapışır, çevresinde sarı bir halka ve büyük bir '!' belirir — bu ısırma anıdır ve sadece 0.7 saniye sürer. O pencerede Boşluk'a basarsan balığı oltaya takarsın; geç kalırsan balık silkinerek kaçar. Bir balık takıldıktan sonra dövüş başlar: alttaki iki çubuk ekrana gelir — soldaki balığın canı, sağdaki misinanın gerilimi. Boşluk'u **basılı tutarsan** misinayı çekersin: balığın canı azalır ama gerilim hızla artar; **bıraktığında** ise gerilim düşer ve balık biraz nefes alır. Sırrı, balık sarsıldığında gerilimin ani sıçramasını okuyup tam o anda Boşluk'u bırakmaktır. Gerilim çubuğu kırmızıya dolup %100'e ulaşırsa misina kopar ve balık gider; balığın canı sıfıra düşerse kayığa alırsın ve puan alırsın. Dövüş 12 saniyeyle sınırlıdır: vakitsiz balık yorulmaz ve kurtulur. Strateji ipucu: küçük balıklar hızlı para ama büyükler asıl puan; büyük balığa yöneldiğinde sabırlı ol, sürekli çekme yerine 'çek-bırak-çek-bırak' ritmi kur; gerilim yarıyı geçince elini bekle, balığın sarsıntısı bitsin sonra tekrar başla. Süre 90 saniyedir ve bittiğinde toplam puanın rekorunla karşılaştırılır.",
  "thumbnail": "olta.svg",
  "scoring": {
    "storageKey": "olta.best",
    "label": "Skor",
    "direction": "higher",
    "labelEn": "Score"
  },
  "en": {
    "title": "Cast Line",
    "description": "One boat, one patient hand, a line under tension — hook the bite at the right instant and reel without snapping.",
    "controls": "↑/↓ or W/S: raise / lower the bait · Space: hook on bite, then hold / release to reel · R: restart",
    "howToPlay": "Cast Line is an original 90-second reflex game that fuses the two distinct skills of fishing — striking at the right moment and managing tension during the fight. A small boat sits on the surface with a line dropping straight down to an orange bait; below it, coloured fish drift sideways at different depths. Small blue fish cruise near the surface (1 point), orange medium fish patrol the middle layer (3 points), and gold large fish swim slowly along the bottom (8 points); pink jellyfish drift through occasionally and are dangerous (-2 points and they ruin your attempt). Move the bait up and down with ↑/↓ or W/S; on mobile, the ▲ and ▼ buttons do the same. When the bait drifts next to a fish, the fish locks on, a yellow ring pulses around the bait and a big '!' appears — that is the bite, and it lasts only 0.7 seconds. Press Space inside that window to set the hook; miss it and the fish thrashes free. Once hooked, the fight begins: two bars appear — the fish's stamina on the left, the line tension on the right. **Holding** Space reels in: the fish's stamina drops but tension climbs fast; **releasing** lets tension fall and the fish recover slightly. The trick is reading the random jolts a hooked fish gives — tension spikes suddenly, and you must release just then. If tension fills to 100% the line snaps and the fish is gone; if the fish's stamina hits zero you land it for the points. The fight is capped at 12 seconds — outlast the clock and the fish escapes unhurt. Tip: small fish are quick points, but the large ones are where the score is; on a big fish, do not hold continuously — pull-release-pull-release in rhythm, and when tension passes the halfway mark, wait out the next jolt before reeling again. The round lasts 90 seconds; at the end your total is compared with your stored best."
  }
}
